Workbook

Sheet Resumen
A1: NeoEduCore — Avance de pendientes
A2: Cuenta solo las tareas principales (tipo «Tarea»); las subtareas se siguen en la hoja Checklist. «Cerradas» = Hecho + Descartado.
A4: Sección | B4: Total | C4: Pendiente | D4: En curso | E4: Hecho | F4: Descartado | G4: Cerradas | H4: % avance
A5: 1. Decisiones que bloquean otras tareas | B5: =COUNTIFS(Checklist!$C$2:$C$327,$A5,Checklist!$B$2:$B$327,"Tarea") | C5: =COUNTIFS(Checklist!$C$2:$C$327,$A5,Checklist!$B$2:$B$327,"Tarea",Checklist!$J$2:$J$327,"Pendiente") | D5: =COUNTIFS(Checklist!$C$2:$C$327,$A5,Checklist!$B$2:$B$327,"Tarea",Checklist!$J$2:$J$327,"En curso") | E5: =COUNTIFS(Checklist!$C$2:$C$327,$A5,Checklist!$B$2:$B$327,"Tarea",Checklist!$J$2:$J$327,"Hecho") | F5: =COUNTIFS(Checklist!$C$2:$C$327,$A5,Checklist!$B$2:$B$327,"Tarea",Checklist!$J$2:$J$327,"Descartado") | G5: =E5+F5 | H5: =IF(B5=0,0,G5/B5)
A6: 2. Seguridad | B6: =COUNTIFS(Checklist!$C$2:$C$327,$A6,Checklist!$B$2:$B$327,"Tarea") | C6: =COUNTIFS(Checklist!$C$2:$C$327,$A6,Checklist!$B$2:$B$327,"Tarea",Checklist!$J$2:$J$327,"Pendiente") | D6: =COUNTIFS(Checklist!$C$2:$C$327,$A6,Checklist!$B$2:$B$327,"Tarea",Checklist!$J$2:$J$327,"En curso") | E6: =COUNTIFS(Checklist!$C$2:$C$327,$A6,Checklist!$B$2:$B$327,"Tarea",Checklist!$J$2:$J$327,"Hecho") | F6: =COUNTIFS(Checklist!$C$2:$C$327,$A6,Checklist!$B$2:$B$327,"Tarea",Checklist!$J$2:$J$327,"Descartado") | G6: =E6+F6 | H6: =IF(B6=0,0,G6/B6)
A7: 3. Producción y despliegue | B7: =COUNTIFS(Checklist!$C$2:$C$327,$A7,Checklist!$B$2:$B$327,"Tarea") | C7: =COUNTIFS(Checklist!$C$2:$C$327,$A7,Checklist!$B$2:$B$327,"Tarea",Checklist!$J$2:$J$327,"Pendiente") | D7: =COUNTIFS(Checklist!$C$2:$C$327,$A7,Checklist!$B$2:$B$327,"Tarea",Checklist!$J$2:$J$327,"En curso") | E7: =COUNTIFS(Checklist!$C$2:$C$327,$A7,Checklist!$B$2:$B$327,"Tarea",Checklist!$J$2:$J$327,"Hecho") | F7: =COUNTIFS(Checklist!$C$2:$C$327,$A7,Checklist!$B$2:$B$327,"Tarea",Checklist!$J$2:$J$327,"Descartado") | G7: =E7+F7 | H7: =IF(B7=0,0,G7/B7)
A8: 4. Mediciones | B8: =COUNTIFS(Checklist!$C$2:$C$327,$A8,Checklist!$B$2:$B$327,"Tarea") | C8: =COUNTIFS(Checklist!$C$2:$C$327,$A8,Checklist!$B$2:$B$327,"Tarea",Checklist!$J$2:$J$327,"Pendiente") | D8: =COUNTIFS(Checklist!$C$2:$C$327,$A8,Checklist!$B$2:$B$327,"Tarea",Checklist!$J$2:$J$327,"En curso") | E8: =COUNTIFS(Checklist!$C$2:$C$327,$A8,Checklist!$B$2:$B$327,"Tarea",Checklist!$J$2:$J$327,"Hecho") | F8: =COUNTIFS(Checklist!$C$2:$C$327,$A8,Checklist!$B$2:$B$327,"Tarea",Checklist!$J$2:$J$327,"Descartado") | G8: =E8+F8 | H8: =IF(B8=0,0,G8/B8)
A9: 5. Frontend | B9: =COUNTIFS(Checklist!$C$2:$C$327,$A9,Checklist!$B$2:$B$327,"Tarea") | C9: =COUNTIFS(Checklist!$C$2:$C$327,$A9,Checklist!$B$2:$B$327,"Tarea",Checklist!$J$2:$J$327,"Pendiente") | D9: =COUNTIFS(Checklist!$C$2:$C$327,$A9,Checklist!$B$2:$B$327,"Tarea",Checklist!$J$2:$J$327,"En curso") | E9: =COUNTIFS(Checklist!$C$2:$C$327,$A9,Checklist!$B$2:$B$327,"Tarea",Checklist!$J$2:$J$327,"Hecho") | F9: =COUNTIFS(Checklist!$C$2:$C$327,$A9,Checklist!$B$2:$B$327,"Tarea",Checklist!$J$2:$J$327,"Descartado") | G9: =E9+F9 | H9: =IF(B9=0,0,G9/B9)
A10: 6. Informe del TFG | B10: =COUNTIFS(Checklist!$C$2:$C$327,$A10,Checklist!$B$2:$B$327,"Tarea") | C10: =COUNTIFS(Checklist!$C$2:$C$327,$A10,Checklist!$B$2:$B$327,"Tarea",Checklist!$J$2:$J$327,"Pendiente") | D10: =COUNTIFS(Checklist!$C$2:$C$327,$A10,Checklist!$B$2:$B$327,"Tarea",Checklist!$J$2:$J$327,"En curso") | E10: =COUNTIFS(Checklist!$C$2:$C$327,$A10,Checklist!$B$2:$B$327,"Tarea",Checklist!$J$2:$J$327,"Hecho") | F10: =COUNTIFS(Checklist!$C$2:$C$327,$A10,Checklist!$B$2:$B$327,"Tarea",Checklist!$J$2:$J$327,"Descartado") | G10: =E10+F10 | H10: =IF(B10=0,0,G10/B10)
A11: 7. Entregables no-código | B11: =COUNTIFS(Checklist!$C$2:$C$327,$A11,Checklist!$B$2:$B$327,"Tarea") | C11: =COUNTIFS(Checklist!$C$2:$C$327,$A11,Checklist!$B$2:$B$327,"Tarea",Checklist!$J$2:$J$327,"Pendiente") | D11: =COUNTIFS(Checklist!$C$2:$C$327,$A11,Checklist!$B$2:$B$327,"Tarea",Checklist!$J$2:$J$327,"En curso") | E11: =COUNTIFS(Checklist!$C$2:$C$327,$A11,Checklist!$B$2:$B$327,"Tarea",Checklist!$J$2:$J$327,"Hecho") | F11: =COUNTIFS(Checklist!$C$2:$C$327,$A11,Checklist!$B$2:$B$327,"Tarea",Checklist!$J$2:$J$327,"Descartado") | G11: =E11+F11 | H11: =IF(B11=0,0,G11/B11)
A12: 8. Mejoras opcionales | B12: =COUNTIFS(Checklist!$C$2:$C$327,$A12,Checklist!$B$2:$B$327,"Tarea") | C12: =COUNTIFS(Checklist!$C$2:$C$327,$A12,Checklist!$B$2:$B$327,"Tarea",Checklist!$J$2:$J$327,"Pendiente") | D12: =COUNTIFS(Checklist!$C$2:$C$327,$A12,Checklist!$B$2:$B$327,"Tarea",Checklist!$J$2:$J$327,"En curso") | E12: =COUNTIFS(Checklist!$C$2:$C$327,$A12,Checklist!$B$2:$B$327,"Tarea",Checklist!$J$2:$J$327,"Hecho") | F12: =COUNTIFS(Checklist!$C$2:$C$327,$A12,Checklist!$B$2:$B$327,"Tarea",Checklist!$J$2:$J$327,"Descartado") | G12: =E12+F12 | H12: =IF(B12=0,0,G12/B12)
A13: 9. Funcionalidad nueva del backend | B13: =COUNTIFS(Checklist!$C$2:$C$327,$A13,Checklist!$B$2:$B$327,"Tarea") | C13: =COUNTIFS(Checklist!$C$2:$C$327,$A13,Checklist!$B$2:$B$327,"Tarea",Checklist!$J$2:$J$327,"Pendiente") | D13: =COUNTIFS(Checklist!$C$2:$C$327,$A13,Checklist!$B$2:$B$327,"Tarea",Checklist!$J$2:$J$327,"En curso") | E13: =COUNTIFS(Checklist!$C$2:$C$327,$A13,Checklist!$B$2:$B$327,"Tarea",Checklist!$J$2:$J$327,"Hecho") | F13: =COUNTIFS(Checklist!$C$2:$C$327,$A13,Checklist!$B$2:$B$327,"Tarea",Checklist!$J$2:$J$327,"Descartado") | G13: =E13+F13 | H13: =IF(B13=0,0,G13/B13)
A14: Total | B14: =SUM(B5:B13) | C14: =SUM(C5:C13) | D14: =SUM(D5:D13) | E14: =SUM(E5:E13) | F14: =SUM(F5:F13) | G14: =SUM(G5:G13) | H14: =IF(B14=0,0,G14/B14)
A16: Prioridad | B16: Total | C16: Pendiente | D16: En curso | E16: Hecho | F16: Descartado | G16: Cerradas | H16: % avance
A17: 1 · Alta | B17: =COUNTIFS(Checklist!$E$2:$E$327,$A17,Checklist!$B$2:$B$327,"Tarea") | C17: =COUNTIFS(Checklist!$E$2:$E$327,$A17,Checklist!$B$2:$B$327,"Tarea",Checklist!$J$2:$J$327,"Pendiente") | D17: =COUNTIFS(Checklist!$E$2:$E$327,$A17,Checklist!$B$2:$B$327,"Tarea",Checklist!$J$2:$J$327,"En curso") | E17: =COUNTIFS(Checklist!$E$2:$E$327,$A17,Checklist!$B$2:$B$327,"Tarea",Checklist!$J$2:$J$327,"Hecho") | F17: =COUNTIFS(Checklist!$E$2:$E$327,$A17,Checklist!$B$2:$B$327,"Tarea",Checklist!$J$2:$J$327,"Descartado") | G17: =E17+F17 | H17: =IF(B17=0,0,G17/B17)
A18: 2 · Media | B18: =COUNTIFS(Checklist!$E$2:$E$327,$A18,Checklist!$B$2:$B$327,"Tarea") | C18: =COUNTIFS(Checklist!$E$2:$E$327,$A18,Checklist!$B$2:$B$327,"Tarea",Checklist!$J$2:$J$327,"Pendiente") | D18: =COUNTIFS(Checklist!$E$2:$E$327,$A18,Checklist!$B$2:$B$327,"Tarea",Checklist!$J$2:$J$327,"En curso") | E18: =COUNTIFS(Checklist!$E$2:$E$327,$A18,Checklist!$B$2:$B$327,"Tarea",Checklist!$J$2:$J$327,"Hecho") | F18: =COUNTIFS(Checklist!$E$2:$E$327,$A18,Checklist!$B$2:$B$327,"Tarea",Checklist!$J$2:$J$327,"Descartado") | G18: =E18+F18 | H18: =IF(B18=0,0,G18/B18)
A19: 3 · Media-baja | B19: =COUNTIFS(Checklist!$E$2:$E$327,$A19,Checklist!$B$2:$B$327,"Tarea") | C19: =COUNTIFS(Checklist!$E$2:$E$327,$A19,Checklist!$B$2:$B$327,"Tarea",Checklist!$J$2:$J$327,"Pendiente") | D19: =COUNTIFS(Checklist!$E$2:$E$327,$A19,Checklist!$B$2:$B$327,"Tarea",Checklist!$J$2:$J$327,"En curso") | E19: =COUNTIFS(Checklist!$E$2:$E$327,$A19,Checklist!$B$2:$B$327,"Tarea",Checklist!$J$2:$J$327,"Hecho") | F19: =COUNTIFS(Checklist!$E$2:$E$327,$A19,Checklist!$B$2:$B$327,"Tarea",Checklist!$J$2:$J$327,"Descartado") | G19: =E19+F19 | H19: =IF(B19=0,0,G19/B19)
A20: 4 · Normal | B20: =COUNTIFS(Checklist!$E$2:$E$327,$A20,Checklist!$B$2:$B$327,"Tarea") | C20: =COUNTIFS(Checklist!$E$2:$E$327,$A20,Checklist!$B$2:$B$327,"Tarea",Checklist!$J$2:$J$327,"Pendiente") | D20: =COUNTIFS(Checklist!$E$2:$E$327,$A20,Checklist!$B$2:$B$327,"Tarea",Checklist!$J$2:$J$327,"En curso") | E20: =COUNTIFS(Checklist!$E$2:$E$327,$A20,Checklist!$B$2:$B$327,"Tarea",Checklist!$J$2:$J$327,"Hecho") | F20: =COUNTIFS(Checklist!$E$2:$E$327,$A20,Checklist!$B$2:$B$327,"Tarea",Checklist!$J$2:$J$327,"Descartado") | G20: =E20+F20 | H20: =IF(B20=0,0,G20/B20)
A21: Total | B21: =SUM(B17:B20) | C21: =SUM(C17:C20) | D21: =SUM(D17:D20) | E21: =SUM(E17:E20) | F21: =SUM(F17:F20) | G21: =SUM(G17:G20) | H21: =IF(B21=0,0,G21/B21)

Sheet Checklist
A1: Código | B1: Tipo | C1: Sección | D1: Subsección | E1: Prioridad | F1: Tarea | G1: Detalle | H1: Depende de | I1: Fuente | J1: Estado | K1: Fecha cierre | L1: Notas
A2: D1 | B2: Tarea | C2: 1. Decisiones que bloquean otras tareas | E2: 1 · Alta | F2: Recomendaciones post-examen: IA diferida a la cola | G2: • Hoy el submit las genera con un if/elseif/else sobre el porcentaje, sin OpenAI; la IA solo entra al pulsar regenerar. • (a) Diferir la generación IA a la cola → código: job, estado «en preparación», aviso al frontend. • (b) Reescribir [122], [222], [255] y [736] para describir heurística inmediata + IA bajo demanda → cero código. • Bloquea: capítulo del tutor (I-3). | I2: ESTADO_Y_PENDIENTES.md §3.6 nº 1 | J2: Hecho | K2: 46278 | L2: Elegida (a). Disparador: la consulta de resultados, no la entrega. Job GenerateAiRecommendations + attempt_id/generated_by/ai_recommendations_status. Migracion 2026_09_13_000001 aplicada. Depende de P1 (worker) y P2 (QUEUE_CONNECTION).
A3: D2 | B3: Tarea | C3: 1. Decisiones que bloquean otras tareas | E3: 1 · Alta | F3: Metadatos curriculares de questions y subject_id en study_resources | G3: • Añadir las columnas o recortar la promesa en [171], [222], [263] y [276]. • Bloquea: banco de 60 ítems (E2), diagnóstico por tema, «temas más recomendados» para el docente, recursos por materia. | I3: ESTADO_Y_PENDIENTES.md §3.6 nº 7 | J3: Hecho | K3: 46278 | L3: Se anadieron las columnas, alcance completo. topic_normalized es columna generada por PostgreSQL. Tema como texto libre normalizado, no catalogo. Migracion 2026_09_13_000002 aplicada. Desbloquea E2 y cierra K2, K3 y K4.
A4: D3 | B4: Tarea | C4: 1. Decisiones que bloquean otras tareas | E4: 1 · Alta | F4: Expiracion de sesion: inactividad de 60 min | G4: • config/sanctum.php:50 → SANCTUM_TOKEN_EXPIRATION_MINUTES, 720 por defecto. • Recomendado: bajar la variable (cuentas de menores en equipos compartidos) en vez de relajar el requisito. • Si se baja: ajustar .env.example y fijarlo en Coolify (P2). | I4: ESTADO_Y_PENDIENTES.md §9.3 · ANALISIS_MODELO_DATOS_TFG.md §10.2 nº 9 | J4: Hecho | K4: 46278 | L4: Inactividad real de 60 min sobre last_used_at (SANCTUM_TOKEN_INACTIVITY_MINUTES), no expiracion absoluta. Bajar EXPIRATION a 60 habria expulsado al alumno a mitad de un examen de hasta 300 min. Via Sanctum::authenticateAccessTokensUsing(), no middleware. Cierra K9 e I-11.
A5: D4 | B5: Tarea | C5: 1. Decisiones que bloquean otras tareas | E5: 3 · Media-baja | F5: Aviso de «esta respuesta la genera una IA» ([397]) | G5: • Campo en la respuesta de POST /ai/tutor/chat (hoy {session_id, reply, message_count}) o el informe lo atribuye a la interfaz. | I5: ESTADO_Y_PENDIENTES.md §3.6 nº 8 | J5: Hecho | K5: 46278 | L5: Campo ai_notice en la respuesta del chat y del diagnostico. Texto en openai.tutor.notice (OPENAI_TUTOR_NOTICE). Se eligio el sistema y no el frontend: el compromiso de [397] es del sistema. Cierra K5.
A6: D5 | B6: Tarea | C6: 1. Decisiones que bloquean otras tareas | E6: 3 · Media-baja | F6: Registro de incidencias del tutor IA | G6: • Hoy los bloqueos por PII o enlace no permitido solo dejan Log::warning. • Crear tabla/contador o retirar del informe el criterio «>75 % de mensajes que superen validación». | I6: ESTADO_Y_PENDIENTES.md §9.3 · §3.6 nº 6 | J6: Hecho | K6: 46278 | L6: Tabla ai_tutor_incidents (migracion 2026_09_13_000003, aplicada) + GET /platform/ai-tutor-metrics solo superadmin, solo agregados. NO guarda el texto que provoco la incidencia. Cierra K6.
A7: D6 | B7: Tarea | C7: 1. Decisiones que bloquean otras tareas | E7: 4 · Normal | F7: PATCH /users/{id}/reset-password no activa la cuenta | G7: • Coherente con «la activa su dueño», pero confunde a soporte. ¿Se deja, se activa o se documenta? | I7: ESTADO_Y_PENDIENTES.md §8 | J7: Hecho | K7: 46278 | L7: Se queda sin activar (la regla no se toca) pero la respuesta devuelve status, can_sign_in y activation_needed, y el mensaje dice que hay que enviar el enlace de activacion.
A8: D7 | B8: Tarea | C8: 1. Decisiones que bloquean otras tareas | E8: 4 · Normal | F8: available-exams muestra max_attempts al alumno | G8: • Se dejó para poder mostrar «intento 2 de 3». Confirmar. | J8: Hecho | K8: 46278 | L8: Confirmado: se queda. Sin cambios de codigo. Con max_attempts y submitted_count el frontend pinta «intento 2 de 3». No es informacion sensible.
A9: D8 | B9: Tarea | C9: 1. Decisiones que bloquean otras tareas | E9: 4 · Normal | F9: ¿Formalizar ENABLE ROW LEVEL SECURITY en una migración? | G9: • Hoy lo pone Supabase; un PostgreSQL que no sea Supabase no lo tendría. | I9: ESTADO_Y_PENDIENTES.md §5, pendientes 31/07 | J9: Hecho | K9: 46278 | L9: Migracion 2026_09_13_000004 sobre 26 tablas, idempotente, aplicada. RLS sin politicas no afecta a la app (su rol es propietario); cierra la API REST automatica de Supabase. Ademas schema:dump-sql ya no pierde el bloque.
A10: S1 | B10: Tarea | C10: 2. Seguridad | E10: 1 · Alta | F10: Revisión sistemática de seguridad por rol, endpoint por endpoint | G10: • Pregunta a responder en cada ruta: qué campos ve cada rol, no solo si llega. • Motivo: 5 hallazgos aparecieron por casualidad (G12, 05/08, 07/08, 08/08, 08/08 tarde) y ningún test existente los detectaba. • Herramienta: /security-review o /code-review sobre la rama. | J10: Hecho | K10: 46278 | L10: Revisados los 122 endpoints contra los 4 roles. 1 hallazgo real corregido: /users era puerta paralela a /students (docente sin asignacion listaba a todos los menores con nombre y correo). Blindado por tests/Feature/Security/AlcancePorRolTest.php (13 casos). Deja abiertos S5 y S6.
A11: S2 | B11: Tarea | C11: 2. Seguridad | E11: 1 · Alta | F11: Cambiar la contraseña temporal del superadmin en producción | G11: • POST /api/password/change. Antes de que haya usuarios reales. | J11: Pendiente
A12: S3 | B12: Tarea | C12: 2. Seguridad | E12: 1 · Alta | F12: Credencial de PostgreSQL en el historial de git | J12: Pendiente
A13: S3.1 | B13: Subtarea | C13: 2. Seguridad | E13: 1 · Alta | F13: Rotar esa contraseña si sigue viva en alguna base. | J13: Pendiente
A14: S3.2 | B14: Subtarea | C14: 2. Seguridad | E14: 1 · Alta | F14: Decidir con el equipo si se limpia el historial (git filter-repo/BFG + push forzado a Infil505/NeoEduCore-Back; afecta a los otros proponentes). | J14: Pendiente
A15: S4 | B15: Tarea | C15: 2. Seguridad | E15: 2 · Media | F15: Posible inyección de fórmulas en los CSV exportados | G15: • (por verificar) • ReportExportService::streamCsv() escribe con fputcsv los textos tal cual. Si un nombre de alumno, título de examen o materia empieza por =, +, - o @, Excel lo ejecuta como fórmula al abrir el CSV (p. ej. =HYPERLINK(...)). • Ninguna validación lo impide: full_name solo exige string, min y max. • Corrección habitual: anteponer ' a esas celdas al exportar. Hacerlo junto con B1, que toca el mismo servicio. • Detectado el 10/09/2026 al revisar el servicio para anotar B1; no se ha comprobado con una petición real. | J15: Hecho | K15: 46278 | L15: Confirmado y corregido. CSV neutraliza con apóstrofo; XLSX escribe tipo texto explícito. Cubierto por tests/Feature/Crud/ReportExportsTest.php.
A16: P1 | B16: Tarea | C16: 3. Producción y despliegue | E16: 1 · Alta | F16: Desplegar el código en Coolify | G16: • Las migraciones ya están en producción; los cambios de permisos solo entran al desplegar. | I16: DEPLOY_COOLIFY.md §2–5 | J16: Pendiente
A17: P1.1 | B17: Subtarea | C17: 3. Producción y despliegue | E17: 1 · Alta | F17: Recurso App (Octane + FrankenPHP) | J17: Pendiente
A18: P1.2 | B18: Subtarea | C18: 3. Producción y despliegue | E18: 1 · Alta | F18: Recurso Worker (queue:work) | G18: • Imprescindible desde D1: sin el, los intentos se quedan en «preparing» y el alumno nunca ve el analisis. | J18: Pendiente
A19: P1.3 | B19: Subtarea | C19: 3. Producción y despliegue | E19: 1 · Alta | F19: Scheduled task (schedule:run) | J19: Pendiente
A20: P2 | B20: Tarea | C20: 3. Producción y despliegue | E20: 1 · Alta | F20: Variables de entorno en Coolify | G20: • (el .env local no llega al servidor) | J20: Pendiente
A21: P2.1 | B21: Subtarea | C21: 3. Producción y despliegue | E21: 1 · Alta | F21: CACHE_STORE distinto de array — si no, ningún rate limiter es global | J21: Pendiente
A22: P2.2 | B22: Subtarea | C22: 3. Producción y despliegue | E22: 1 · Alta | F22: TRUSTED_PROXIES — si no, todos los límites por IP agrupan a los usuarios y el sistema se autobloquea | J22: Pendiente
A23: P2.3 | B23: Subtarea | C23: 3. Producción y despliegue | E23: 1 · Alta | F23: APP_NAME=NeoEduCore | J23: Pendiente
A24: P2.4 | B24: Subtarea | C24: 3. Producción y despliegue | E24: 1 · Alta | F24: APP_URL=https://<dominio real> — y registrar la URL real en DEPLOY_COOLIFY.md:44 (hoy https://tu-dominio) | J24: Pendiente
A25: P2.5 | B25: Subtarea | C25: 3. Producción y despliegue | E25: 1 · Alta | F25: OPENAI_REQUEST_TIMEOUT=15 | J25: Pendiente
A26: P2.6 | B26: Subtarea | C26: 3. Producción y despliegue | E26: 1 · Alta | F26: DB_STATEMENT_TIMEOUT_MS=15000 | J26: Pendiente
A27: P2.7 | B27: Subtarea | C27: 3. Producción y despliegue | E27: 1 · Alta | F27: SANCTUM_TOKEN_EXPIRATION_MINUTES=720 y SANCTUM_TOKEN_INACTIVITY_MINUTES=60 | G27: • Las dos, segun D3. • EXPIRATION es el tope absoluto de jornada; INACTIVITY es lo que exige [758]. | H27: D3 | J27: Pendiente
A28: P3 | B28: Tarea | C28: 3. Producción y despliegue | E28: 1 · Alta | F28: Cargar las asignaciones de docentes | G28: • (POST /api/teacher-assignments) • La tabla nace vacía a propósito: hasta entonces ningún docente ve a ningún estudiante. | J28: Pendiente
A29: P4 | B29: Tarea | C29: 3. Producción y despliegue | E29: 2 · Media | F29: Cloudflare delante del dominio + sus rangos en TRUSTED_PROXIES, en el mismo cambio | G29: • ⚠️ Lo primero sin lo segundo deja el sistema peor que ahora. | I29: DEPLOY_COOLIFY.md §9 | J29: Pendiente
A30: P5 | B30: Tarea | C30: 3. Producción y despliegue | E30: 4 · Normal | F30: Rate limiting en Traefik | G30: • como segunda capa | J30: Pendiente
A31: P6 | B31: Tarea | C31: 3. Producción y despliegue | E31: 2 · Media | F31: Backups cifrados de la base de datos | G31: • no hay script ni documentación (RNF de seguridad) | J31: Pendiente
A32: P7 | B32: Tarea | C32: 3. Producción y despliegue | E32: 2 · Media | F32: Monitoreo y alertas de caída | G32: • Sentry o equivalente (RNF de disponibilidad) | J32: Pendiente
A33: P8 | B33: Tarea | C33: 3. Producción y despliegue | E33: 4 · Normal | F33: Documentar HTTPS/TLS | G33: • en DEPLOY_COOLIFY.md (lo resuelve Coolify, pero debe quedar escrito) | J33: Pendiente
A34: M1 | B34: Tarea | C34: 4. Mediciones | E34: 1 · Alta | F34: Verificar que $request->ip() devuelve IPs reales | G34: • en producción y no la de Traefik | H34: P1–P2 | J34: Pendiente
A35: M2 | B35: Tarea | C35: 4. Mediciones | E35: 4 · Normal | F35: RTT real del contenedor a Supabase | G35: • psql "$DATABASE_URL" -c '\timing on' -c 'SELECT 1;' desde el contenedor desplegado. | H35: P1–P2 | I35: ANALISIS_CONCURRENCIA.md §6.5 | J35: Pendiente
A36: M3 | B36: Tarea | C36: 4. Mediciones | E36: 4 · Normal | F36: Prueba de carga contra el despliegue real con Octane | G36: • (valida «200 concurrentes») • k6 run -e BASE_URL=https://<host>/api -e VUS=50 -e DURATION=60s k6/exam_peak.js | H36: P1–P2 | J36: Pendiente
A37: M4 | B37: Tarea | C37: 4. Mediciones | E37: 2 · Media | F37: Informe de cobertura ≥ 70 % | G37: • php artisan test --coverage --min=70 (requiere Xdebug o PCOV). | J37: Hecho | K37: 46298 | L37: Líneas 91,36 % (4271/4675) sobre 565 tests; excluye app/Console y ApiSpec (herramientas de desarrollo). Antes 77,80 %
A38: F1 | B38: Tarea | C38: 5. Frontend | D38: Funcionalidad nueva | E38: 1 · Alta | F38: PDF de reportes | G38: • con gráficos de barras, líneas y pastel • Datos: GET /reports/exams/{id}/summary y GET /reports/students/{id}/summary. • performance_levels son categorías ordenadas: rampa de un solo tono, nunca verde/rojo. • Hasta que exista, [236] del informe sigue siendo parcialmente falsa. | J38: Pendiente
A39: F2 | B39: Tarea | C39: 5. Frontend | D39: Funcionalidad nueva | E39: 1 · Alta | F39: PDF de estrategias del tutor | G39: • Datos: GET /reports/students/me/strategies y GET /reports/students/{id}/strategies. | J39: Pendiente
A40: F3 | B40: Tarea | C40: 5. Frontend | D40: Funcionalidad nueva | E40: 1 · Alta | F40: Panel de superadmin | G40: • instituciones y sus administradores | J40: Pendiente
A41: F4 | B41: Tarea | C41: 5. Frontend | D41: Funcionalidad nueva | E41: 1 · Alta | F41: Pantalla de admin para asignar docentes | G41: • (/api/teacher-assignments) | J41: Pendiente
A42: F5 | B42: Tarea | C42: 5. Frontend | D42: Funcionalidad nueva | E42: 4 · Normal | F42: Confirmación antes de borrar | G42: • materias/grupos/exámenes/usuarios, mostrando exams_count (los borrados cascadean a resultados de alumnos) | J42: Pendiente
A43: F6 | B43: Tarea | C43: 5. Frontend | D43: Funcionalidad nueva | E43: 4 · Normal | F43: Saludo con el nombre del alumno en el tutor | G43: • (el backend ya no lo envía a OpenAI) | J43: Pendiente
A44: F7 | B44: Tarea | C44: 5. Frontend | D44: Funcionalidad nueva | E44: 4 · Normal | F44: Aviso de IA en cada respuesta del tutor | G44: • (según D4) | H44: D4 | J44: Pendiente | L44: Listo para consumir: el backend lo manda en data.ai_notice (D4).
A45: F8 | B45: Tarea | C45: 5. Frontend | D45: Funcionalidad nueva | E45: 4 · Normal | F45: Cargar el diagnóstico automáticamente al abrir el tutor | G45: • (GET /ai/tutor/diagnosis) | J45: Pendiente
A46: F9 | B46: Tarea | C46: 5. Frontend | D46: Funcionalidad nueva | E46: 4 · Normal | F46: Contexto exam_id opcional en el chat del tutor | J46: Pendiente
A47: F10 | B47: Tarea | C47: 5. Frontend | D47: Adaptaciones a cambios que rompen | E47: 1 · Alta | F47: Publicar/activar exámenes con PATCH /exams/{id}/status | G47: • sin esto ningún examen sale de draft | J47: Pendiente
A48: F11 | B48: Tarea | C48: 5. Frontend | D48: Adaptaciones a cambios que rompen | E48: 1 · Alta | F48: Vista del alumno con GET /students/me/available-exams | G48: • en vez de GET /exams | J48: Pendiente
A49: F12 | B49: Tarea | C49: 5. Frontend | D49: Adaptaciones a cambios que rompen | E49: 1 · Alta | F49: Docente acotado a sus grupos asignados | J49: Pendiente
A50: F12.1 | B50: Subtarea | C50: 5. Frontend | D50: Adaptaciones a cambios que rompen | E50: 1 · Alta | F50: GET /students, GET /groups e informes devuelven solo lo asignado (403 fuera) | J50: Pendiente
A51: F12.2 | B51: Subtarea | C51: 5. Frontend | D51: Adaptaciones a cambios que rompen | E51: 1 · Alta | F51: POST/DELETE /groups/{id}/students pasó a admin-only | J51: Pendiente
A52: F12.3 | B52: Subtarea | C52: 5. Frontend | D52: Adaptaciones a cambios que rompen | E52: 1 · Alta | F52: Crear examen con grupo no asignado → 403 con grupos_no_asignados | J52: Pendiente
A53: F13 | B53: Tarea | C53: 5. Frontend | D53: Adaptaciones a cambios que rompen | E53: 4 · Normal | F53: Admin sin acceso a /api/institutions | G53: • → leer su institución por GET /api/system/config | J53: Pendiente
A54: F14 | B54: Tarea | C54: 5. Frontend | D54: Adaptaciones a cambios que rompen | E54: 4 · Normal | F54: Plantilla de carga masiva nueva | G54: • columna aula obligatoria; fuera grade, section, group_code. Bajarla de /api/students/bulk-upload/template | J54: Pendiente
A55: F15 | B55: Tarea | C55: 5. Frontend | D55: Adaptaciones a cambios que rompen | E55: 4 · Normal | F55: Cuentas de carga masiva nacen inactivas | G55: • hasta que el dueño define su contraseña | J55: Pendiente
A56: F16 | B56: Tarea | C56: 5. Frontend | D56: Adaptaciones a cambios que rompen | E56: 4 · Normal | F56: GET /ai-recommendations ya no lista al docente las de exámenes ajenos | J56: Pendiente
A57: I-1 | B57: Tarea | C57: 6. Informe del TFG | D57: Correcciones críticas | E57: 1 · Alta | F57: Stack tecnológico | G57: • ANALISIS_MODELO_DATOS_TFG.md §9.1 | J57: Pendiente
A58: I-1.1 | B58: Subtarea | C58: 6. Informe del TFG | D58: Correcciones críticas | E58: 1 · Alta | F58: Quitar Node.js como capa de datos intermediaria | J58: Pendiente
A59: I-1.2 | B59: Subtarea | C59: 6. Informe del TFG | D59: Correcciones críticas | E59: 1 · Alta | F59: Quitar Next.js → React 19 + Vite + TypeScript | J59: Pendiente
A60: I-1.3 | B60: Subtarea | C60: 6. Informe del TFG | D60: Correcciones críticas | E60: 1 · Alta | F60: JWT → Laravel Sanctum | J60: Pendiente
A61: I-1.4 | B61: Subtarea | C61: 6. Informe del TFG | D61: Correcciones críticas | E61: 1 · Alta | F61: Render/Railway → DigitalOcean + Coolify + Supabase | J61: Pendiente
A62: I-2 | B62: Tarea | C62: 6. Informe del TFG | D62: Correcciones críticas | E62: 1 · Alta | F62: Relación docente↔estudiante vía teacher_assignments | G62: • (§9.8.5) | J62: Pendiente
A63: I-3 | B63: Tarea | C63: 6. Informe del TFG | D63: Correcciones críticas | E63: 1 · Alta | F63: Capítulo del tutor | G63: • según D1 | H63: D1 | J63: Pendiente | L63: D1 cerrada por codigo: el capitulo puede describir el sistema tal cual, sin recortar la promesa.
A64: I-4 | B64: Tarea | C64: 6. Informe del TFG | D64: Modelo de datos y diagramas | E64: 2 · Media | F64: Incorporar al .docx los 16 diagramas de DIAGRAMAS.md | G64: • (su tabla final dice qué figura sustituye cada uno) | J64: Pendiente
A65: I-5 | B65: Tarea | C65: 6. Informe del TFG | D65: Modelo de datos y diagramas | E65: 2 · Media | F65: Diccionario de datos | G65: • (56 FK, 21 tablas de dominio = 17 entidades + 4 pivotes — cifras al 03/10/2026) | J65: Pendiente
A66: I-6 | B66: Tarea | C66: 6. Informe del TFG | D66: Modelo de datos y diagramas | E66: 2 · Media | F66: Añadir AiChatSession, StudentSubject, TeacherAssignment y AiTutorIncident al diagrama de clases | J66: Pendiente
A67: I-7 | B67: Tarea | C67: 6. Informe del TFG | D67: Modelo de datos y diagramas | E67: 2 · Media | F67: Nombrar los 4 roles reales | G67: • (superadmin, admin, teacher, student) y la frontera superadmin/admin (§9.6) | J67: Pendiente
A68: I-8 | B68: Tarea | C68: 6. Informe del TFG | D68: Modelo de datos y diagramas | E68: 3 · Media-baja | F68: Justificar las 2 decisiones de diseño | G68: • de §4 | J68: Pendiente
A69: I-9 | B69: Tarea | C69: 6. Informe del TFG | D69: Requisitos no funcionales | E69: 3 · Media-baja | F69: Rendimiento: | G69: • ≤2 s y reporte de 1.000 en <5 s están medidos; «200 concurrentes» según M3 | H69: M3 | J69: Pendiente
A70: I-10 | B70: Tarea | C70: 6. Informe del TFG | D70: Requisitos no funcionales | E70: 4 · Normal | F70: Disponibilidad 99 %: | G70: • declarar que no se sostiene solo con la aplicación (requiere P4) | H70: P4 | J70: Pendiente
A71: I-11 | B71: Tarea | C71: 6. Informe del TFG | D71: Requisitos no funcionales | E71: 4 · Normal | F71: Expiración de sesión | G71: • según D3 | H71: D3 | J71: Pendiente | L71: Se cumple [758] desde D3. Explicar que es inactividad y no expiracion absoluta, y por que.
A72: C1 | B72: Tarea | C72: 6. Informe del TFG | D72: Contradicciones internas — §10.1 | E72: 4 · Normal | F72: Tutor «a estudiantes y docentes» [165][505] vs. docente sin mensajes individuales [173] | J72: Pendiente
A73: C2 | B73: Tarea | C73: 6. Informe del TFG | D73: Contradicciones internas — §10.1 | E73: 4 · Normal | F73: Revisión periódica docente del contenido [396] vs. docente no ve mensajes [173] | J73: Pendiente
A74: C3 | B74: Tarea | C74: 6. Informe del TFG | D74: Contradicciones internas — §10.1 | E74: 4 · Normal | F74: Recomendaciones por estudiante [737][739] vs. [173] — reformular como *conversación vs. recomendación* | J74: Pendiente
A75: C4 | B75: Tarea | C75: 6. Informe del TFG | D75: Contradicciones internas — §10.1 | E75: 4 · Normal | F75: React+Next.js [225][804] vs. React+TS sin SSR [296-297][417-418] | J75: Pendiente
A76: C5 | B76: Tarea | C76: 6. Informe del TFG | D76: Contradicciones internas — §10.1 | E76: 4 · Normal | F76: Node.js intermediario [419-420] vs. Laravel+PostgreSQL [228-229][415-416] | J76: Pendiente
A77: C6 | B77: Tarea | C77: 6. Informe del TFG | D77: Contradicciones internas — §10.1 | E77: 4 · Normal | F77: «Genera PDF y CSV» en presente [236] vs. requisito pendiente [732] | J77: Pendiente
A78: C7 | B78: Tarea | C78: 6. Informe del TFG | D78: Contradicciones internas — §10.1 | E78: 4 · Normal | F78: «Se generó reportes en PDF» [390] vs. [732-733] | J78: Pendiente
A79: C8 | B79: Tarea | C79: 6. Informe del TFG | D79: Contradicciones internas — §10.1 | E79: 4 · Normal | F79: Criterio 75 % automático [173] vs. revisión humana [396] | J79: Pendiente | L79: El 75 % ya es medible (D5); queda decidir que dice el informe sobre la revision humana.
A80: K1 | B80: Tarea | C80: 6. Informe del TFG | D80: Contradicciones con el sistema — §10.2 | E80: 4 · Normal | F80: Recomendaciones generadas por IA [122][222][255][737] → según D1 | H80: D1 | J80: Descartado | K80: 46278 | L80: Ya no es contradiccion: D1 se resolvio por codigo.
A81: K2 | B81: Tarea | C81: 6. Informe del TFG | D81: Contradicciones con el sistema — §10.2 | E81: 4 · Normal | F81: Ítems con tema/indicador/dificultad [171][222] → según D2 | H81: D2 | J81: Descartado | K81: 46278 | L81: Las columnas existen (D2).
A82: K3 | B82: Tarea | C82: 6. Informe del TFG | D82: Contradicciones con el sistema — §10.2 | E82: 4 · Normal | F82: Personalización por área concreta («comprensión de lectura») [263][276] → por materia | J82: Descartado | K82: 46278 | L82: El diagnostico del tutor ya habla por tema (D2).
A83: K4 | B83: Tarea | C83: 6. Informe del TFG | D83: Contradicciones con el sistema — §10.2 | E83: 4 · Normal | F83: «Recursos personalizados» (Figura 10) → por grado y dificultad, no por materia | J83: Descartado | K83: 46278 | L83: El recurso sugerido se acota por materia, grado y dificultad (D2).
A84: K5 | B84: Tarea | C84: 6. Informe del TFG | D84: Contradicciones con el sistema — §10.2 | E84: 4 · Normal | F84: Aviso de IA en cada intervención [397] → según D4 | H84: D4 | J84: Descartado | K84: 46278 | L84: El sistema envia el aviso en ai_notice (D4).
A85: K6 | B85: Tarea | C85: 6. Informe del TFG | D85: Contradicciones con el sistema — §10.2 | E85: 4 · Normal | F85: «Registrará incidencias» / 75 % [173] → según D5 | H85: D5 | J85: Descartado | K85: 46278 | L85: Hay tabla de incidencias y el 75 % se calcula (D5).
A86: K7 | B86: Tarea | C86: 6. Informe del TFG | D86: Contradicciones con el sistema — §10.2 | E86: 4 · Normal | F86: «2–4 oraciones» [173] vs. prompt de «máximo 4 párrafos» | J86: Pendiente
A87: K8 | B87: Tarea | C87: 6. Informe del TFG | D87: Contradicciones con el sistema — §10.2 | E87: 4 · Normal | F87: «GPT-4 variante ligera» [222] → gpt-4o-mini (variante de GPT-4o) | J87: Pendiente
A88: K9 | B88: Tarea | C88: 6. Informe del TFG | D88: Contradicciones con el sistema — §10.2 | E88: 4 · Normal | F88: Sesión de 60 min [758] → según D3 | H88: D3 | J88: Descartado | K88: 46278 | L88: El sistema caduca por inactividad a los 60 min (D3).
A89: K10 | B89: Tarea | C89: 6. Informe del TFG | D89: Contradicciones con el sistema — §10.2 | E89: 4 · Normal | F89: «OpenAPI 5.0» [771] → OpenAPI 3.0 (la 5.0 no existe) | J89: Pendiente
A90: K11 | B90: Tarea | C90: 6. Informe del TFG | D90: Contradicciones con el sistema — §10.2 | E90: 4 · Normal | F90: Tres roles [720] → cuatro (ver I-7) | J90: Pendiente
A91: Cap. 3 | B91: Tarea | C91: 6. Informe del TFG | D91: Capítulos | E91: 4 · Normal | F91: Metodología | G91: • Scrum e instrumentos de recolección | J91: Pendiente
A92: Cap. 5 | B92: Tarea | C92: 6. Informe del TFG | D92: Capítulos | E92: 4 · Normal | F92: Conclusiones y recomendaciones | J92: Pendiente
A93: Cap. 7 | B93: Tarea | C93: 6. Informe del TFG | D93: Capítulos | E93: 4 · Normal | F93: Validación y resultados del piloto | G93: • requiere E4 | H93: E4 | J93: Pendiente
A94: Cap. 8 | B94: Tarea | C94: 6. Informe del TFG | D94: Capítulos | E94: 4 · Normal | F94: Discusión de resultados | G94: • requiere E4 | H94: E4 | J94: Pendiente
A95: Cap. 9 | B95: Tarea | C95: 6. Informe del TFG | D95: Capítulos | E95: 4 · Normal | F95: Aspectos éticos, legales y de privacidad | G95: • datos de menores, tutor IA, Ley 8968 | J95: Pendiente
A96: Cap. 10 | B96: Tarea | C96: 6. Informe del TFG | D96: Capítulos | E96: 4 · Normal | F96: Trabajo futuro y escalabilidad | J96: Pendiente
A97: Cap. 11 | B97: Tarea | C97: 6. Informe del TFG | D97: Capítulos | E97: 4 · Normal | F97: Gestión del proyecto | G97: • sprints, hitos, riesgos | J97: Pendiente
A98: Cap. 1 | B98: Tarea | C98: 6. Informe del TFG | D98: Capítulos | E98: 4 · Normal | F98: Introducción | G98: • completar (parcial) | J98: Pendiente
A99: Cap. 2 | B99: Tarea | C99: 6. Informe del TFG | D99: Capítulos | E99: 4 · Normal | F99: Marco teórico | G99: • completar (parcial) | J99: Pendiente
A100: Cap. 4 | B100: Tarea | C100: 6. Informe del TFG | D100: Capítulos | E100: 4 · Normal | F100: Resultados | G100: • completar (parcial) | J100: Pendiente
...
